plant/__init__.py
plant/cli.py
plant/locker.py
auditree_plant-1.0.0.dist-info/LICENSE
auditree_plant-1.0.0.dist-info/METADATA
auditree_plant-1.0.0.dist-info/WHEEL
auditree_plant-1.0.0.dist-info/entry_points.txt
auditree_plant-1.0.0.dist-info/top_level.txt
auditree_plant-1.0.0.dist-info/RECORD
