Metadata-Version: 2.1
Name: auditree-plant
Version: 1.0.0
Summary: The Auditree tool for adding external evidence
Home-page: https://auditree.github.io/
Author: Auditree Security and Compliance
Author-email: al.finkelstein@ibm.com
License: Apache License 2.0
Platform: UNKNOWN
Classifier: Programming Language :: Python :: 3.6
Classifier: Programming Language :: Python :: 3.7
Classifier: Programming Language :: Python :: 3.8
Classifier: Programming Language :: Python :: 3.9
Classifier: License :: OSI Approved :: Apache Software License
Classifier: Operating System :: MacOS :: MacOS X
Classifier: Operating System :: POSIX :: Linux
Requires-Dist: auditree-framework (>=1.0.0)
Provides-Extra: dev
Requires-Dist: pre-commit (>=2.4.0) ; extra == 'dev'
Requires-Dist: pytest (>=4.4.1) ; extra == 'dev'
Requires-Dist: pytest-cov (>=2.6.1) ; extra == 'dev'
Requires-Dist: recommonmark ; extra == 'dev'
Requires-Dist: Sphinx (>=1.7.2) ; extra == 'dev'
Requires-Dist: setuptools ; extra == 'dev'
Requires-Dist: wheel ; extra == 'dev'
Requires-Dist: twine ; extra == 'dev'
